{"halls":[{"id":1,"name":"Hall 1","block":"E","floor":"ground","floorLabel":"Ground Floor","blockColor":"#2563eb","aisles":["E-01","E-02","E-03","E-04"],"aisleCount":4,"stallsPerAisleRow":28,"totalStalls":224,"gridCols":28,"description":"Block E – Ground Floor","specialZones":[{"type":"entrance","label":"ENTRANCE","position":"left"},{"type":"service","label":"SERVICE ENTRY","position":"right"}],"stats":{"total":224,"available":0,"allotted":0,"reserved":0,"blocked":0,"occupiedPct":0}},{"id":3,"name":"Hall 3","block":"E","floor":"ground","floorLabel":"Ground Floor","blockColor":"#2563eb","aisles":["E-05","E-06","E-07","E-08"],"aisleCount":4,"stallsPerAisleRow":28,"totalStalls":224,"gridCols":28,"description":"Block E – Ground Floor","specialZones":[{"type":"entrance","label":"ENTRANCE","position":"left"},{"type":"service","label":"SERVICE ENTRY","position":"right"}],"stats":{"total":224,"available":0,"allotted":0,"reserved":0,"blocked":0,"occupiedPct":0}},{"id":5,"name":"Hall 5","block":"E","floor":"ground","floorLabel":"Ground Floor","blockColor":"#2563eb","aisles":["E-09","E-10","E-11","E-12"],"aisleCount":4,"stallsPerAisleRow":28,"totalStalls":224,"gridCols":28,"description":"Block E – Ground Floor","specialZones":[{"type":"entrance","label":"ENTRANCE","position":"left"}],"stats":{"total":224,"available":0,"allotted":0,"reserved":0,"blocked":0,"occupiedPct":0}},{"id":7,"name":"Hall 7","block":"E","floor":"ground","floorLabel":"Ground Floor","blockColor":"#2563eb","aisles":["E-13","E-14","E-15","E-16"],"aisleCount":4,"stallsPerAisleRow":28,"totalStalls":224,"gridCols":28,"description":"Block E – Ground Floor","specialZones":[{"type":"entrance","label":"MAIN FOYER","position":"left"}],"stats":{"total":224,"available":0,"allotted":0,"reserved":0,"blocked":0,"occupiedPct":0}},{"id":2,"name":"Hall 2","block":"F","floor":"second","floorLabel":"Second Floor","blockColor":"#7c3aed","aisles":["F-01","F-02","F-03","F-04"],"aisleCount":4,"stallsPerAisleRow":28,"totalStalls":224,"gridCols":28,"description":"Block F – Second Floor","specialZones":[{"type":"entrance","label":"ENTRANCE","position":"left"}],"stats":{"total":224,"available":0,"allotted":0,"reserved":0,"blocked":0,"occupiedPct":0}},{"id":4,"name":"Hall 4","block":"F","floor":"second","floorLabel":"Second Floor","blockColor":"#7c3aed","aisles":["F-05","F-06","F-07","F-08"],"aisleCount":4,"stallsPerAisleRow":28,"totalStalls":224,"gridCols":28,"description":"Block F – Second Floor","specialZones":[{"type":"entrance","label":"ENTRANCE","position":"left"}],"stats":{"total":224,"available":0,"allotted":0,"reserved":0,"blocked":0,"occupiedPct":0}},{"id":6,"name":"Hall 6","block":"F","floor":"second","floorLabel":"Second Floor","blockColor":"#7c3aed","aisles":["F-09","F-10","F-11","F-12"],"aisleCount":4,"stallsPerAisleRow":28,"totalStalls":224,"gridCols":28,"description":"Block F – Second Floor","specialZones":[{"type":"entrance","label":"ENTRANCE","position":"left"}],"stats":{"total":224,"available":0,"allotted":0,"reserved":0,"blocked":0,"occupiedPct":0}},{"id":8,"name":"Hall 8","block":"F","floor":"second","floorLabel":"Second Floor","blockColor":"#7c3aed","aisles":["F-13","F-14","F-15","F-16"],"aisleCount":4,"stallsPerAisleRow":28,"totalStalls":224,"gridCols":28,"description":"Block F – Second Floor","specialZones":[{"type":"entrance","label":"ENTRANCE","position":"left"}],"stats":{"total":224,"available":0,"allotted":0,"reserved":0,"blocked":0,"occupiedPct":0}},{"id":9,"name":"Hall 9","block":"G","floor":"ground","floorLabel":"Ground Floor","blockColor":"#0891b2","aisles":["G-01","G-02","G-03","G-04"],"aisleCount":4,"stallsPerAisleRow":28,"totalStalls":224,"gridCols":28,"description":"Block G – Ground Floor","specialZones":[{"type":"service","label":"SERVICE ENTRY","position":"right"},{"type":"entrance","label":"ENTRANCE","position":"left"}],"stats":{"total":224,"available":0,"allotted":0,"reserved":0,"blocked":0,"occupiedPct":0}},{"id":10,"name":"Hall 10","block":"G","floor":"ground","floorLabel":"Ground Floor","blockColor":"#0891b2","aisles":["G-05","G-06","G-07","G-08"],"aisleCount":4,"stallsPerAisleRow":28,"totalStalls":224,"gridCols":28,"description":"Block G – Ground Floor","specialZones":[{"type":"service","label":"SERVICE ENTRY","position":"right"},{"type":"entrance","label":"ENTRANCE","position":"left"}],"stats":{"total":224,"available":0,"allotted":0,"reserved":0,"blocked":0,"occupiedPct":0}},{"id":11,"name":"Hall 11","block":"G","floor":"ground","floorLabel":"Ground Floor","blockColor":"#0891b2","aisles":["G-09","G-10","G-11","G-12"],"aisleCount":4,"stallsPerAisleRow":28,"totalStalls":224,"gridCols":28,"description":"Block G – Ground Floor","specialZones":[{"type":"service","label":"SERVICE ENTRY","position":"right"},{"type":"entrance","label":"ENTRANCE","position":"left"}],"stats":{"total":224,"available":0,"allotted":0,"reserved":0,"blocked":0,"occupiedPct":0}},{"id":12,"name":"Hall 12","block":"G","floor":"ground","floorLabel":"Ground Floor","blockColor":"#0891b2","aisles":["G-13","G-14","G-15","G-16"],"aisleCount":4,"stallsPerAisleRow":28,"totalStalls":224,"gridCols":28,"description":"Block G – Ground Floor","specialZones":[{"type":"service","label":"SERVICE ENTRY","position":"right"},{"type":"entrance","label":"ENTRANCE","position":"left"}],"stats":{"total":224,"available":0,"allotted":0,"reserved":0,"blocked":0,"occupiedPct":0}},{"id":13,"name":"Hall 13","block":"H","floor":"ground","floorLabel":"Ground Floor","blockColor":"#d97706","aisles":["H-01","H-02","H-03","H-04"],"aisleCount":4,"stallsPerAisleRow":28,"totalStalls":224,"gridCols":28,"description":"Block H – Ground Floor","specialZones":[],"stats":{"total":224,"available":0,"allotted":0,"reserved":0,"blocked":0,"occupiedPct":0}},{"id":14,"name":"Hall 14","block":"H","floor":"ground","floorLabel":"Ground Floor","blockColor":"#d97706","aisles":["H-05","H-06","H-07","H-08"],"aisleCount":4,"stallsPerAisleRow":28,"totalStalls":224,"gridCols":28,"description":"Block H – Ground Floor","specialZones":[{"type":"lounge","label":"MEETING AREA","position":"left"}],"stats":{"total":224,"available":0,"allotted":0,"reserved":0,"blocked":0,"occupiedPct":0}},{"id":15,"name":"Hall 15","block":"H","floor":"ground","floorLabel":"Ground Floor","blockColor":"#d97706","aisles":["H-09","H-10","H-11","H-12"],"aisleCount":4,"stallsPerAisleRow":28,"totalStalls":224,"gridCols":28,"description":"Block H – Ground Floor","specialZones":[],"stats":{"total":224,"available":0,"allotted":0,"reserved":0,"blocked":0,"occupiedPct":0}},{"id":16,"name":"Hall 16","block":"J","floor":"ground","floorLabel":"Ground Floor","blockColor":"#db2777","aisles":["J-01","J-02","J-03","J-04","J-05","J-06","J-07","J-08"],"aisleCount":8,"stallsPerAisleRow":24,"totalStalls":384,"gridCols":24,"description":"Block J – Ground Floor","specialZones":[{"type":"lounge","label":"PLATINUM LOUNGE","position":"right"},{"type":"area","label":"ARTISANS AREA","position":"right"}],"stats":{"total":384,"available":0,"allotted":0,"reserved":0,"blocked":0,"occupiedPct":0}},{"id":17,"name":"Hall 17","block":"H","floor":"ground","floorLabel":"Ground Floor","blockColor":"#d97706","aisles":["H-13","H-14","H-15","H-16"],"aisleCount":4,"stallsPerAisleRow":28,"totalStalls":224,"gridCols":28,"description":"Block H – Ground Floor","specialZones":[{"type":"lounge","label":"BUYER'S LOUNGE","position":"top-left"},{"type":"area","label":"INAUGURATION","position":"top-right"},{"type":"area","label":"TEA/COFFEE LOUNGE","position":"top-right"}],"stats":{"total":224,"available":0,"allotted":0,"reserved":0,"blocked":0,"occupiedPct":0}}]}